setup.py
bin/eilat
eilat/CookieJar.py
eilat/DatabaseLog.py
eilat/InterceptNAM.py
eilat/MainWin.py
eilat/SanityChecks.py
eilat/WebPage.py
eilat/WebTab.py
eilat/WebView.py
eilat/__init__.py
eilat/global_store.py
eilat/libeilat.py
eilat/options.py
eilat_web_browser.egg-info/PKG-INFO
eilat_web_browser.egg-info/SOURCES.txt
eilat_web_browser.egg-info/dependency_links.txt
eilat_web_browser.egg-info/requires.txt
eilat_web_browser.egg-info/top_level.txt