Metadata-Version: 1.1
Name: eilat-web-browser
Version: 1.5.2
Summary: QTWebkit based web browser
Home-page: http://github.com/jsoffer/eilat
Author: Jaime Soffer
Author-email: Jaime.Soffer@gmail.com
License: BSD
Download-URL: https://github.com/jsoffer/eilat/releases/
Keywords: web browser qt webkit qtwebkit
Platform: Qt
Classifier: Development Status :: 5 - Production/Stable
Classifier: Environment :: X11 Applications :: Qt
Classifier: Intended Audience :: End Users/Desktop
Classifier: License :: OSI Approved :: BSD License
Classifier: Operating System :: POSIX
Classifier: Programming Language :: Python
Classifier: Programming Language :: Python :: 3
Classifier: Topic :: Internet :: WWW/HTTP :: Browsers
